agent_eval/__init__.py
agent_eval/agent_instance.py
agent_eval/agent_set.py
agent_eval_utils/__init__.py
agent_eval_utils/aimp_message_reader.py
agent_eval_utils/aimp_message_writer.py
agent_eval_utils/excel_reader.py
agent_eval_utils/excel_writer.py
vital_agent_eval_cmd/__init__.py
vital_agent_eval_cmd/vital_agent_eval_cmd.py
vital_agent_eval_env-0.0.3.data/scripts/vitalagenteval
vital_ecosystem/__init__.py
vital_ecosystem/account_container.py
vital_ecosystem/channel_container.py
vital_ecosystem/login_container.py
vital_ecosystem/platform_container.py
vital_ecosystem/service_container.py
vital_ecosystem/tick_manager.py
vital_agent_eval_env-0.0.3.dist-info/LICENSE
vital_agent_eval_env-0.0.3.dist-info/METADATA
vital_agent_eval_env-0.0.3.dist-info/WHEEL
vital_agent_eval_env-0.0.3.dist-info/top_level.txt
vital_agent_eval_env-0.0.3.dist-info/RECORD
