Metadata-Version: 2.1
Name: vital-agent-eval-env
Version: 0.0.3
Summary: Vital Agent Eval Env
Home-page: https://github.com/vital-ai/vital-agent-eval-env
Author: Marc Hadfield
Author-email: marc@vital.ai
License: Apache License 2.0
Classifier: Programming Language :: Python :: 3.10
Classifier: License :: OSI Approved :: Apache Software License
Classifier: Operating System :: OS Independent
Requires-Python: >=3.10
License-File: LICENSE
Requires-Dist: vital-ai-vitalsigns >=0.1.20
Requires-Dist: vital-ai-aimp >=0.1.6
Requires-Dist: vital-agent-container-client >=0.0.3
Requires-Dist: openpyxl
Requires-Dist: vital-agent-kg-utils >=0.1.1
Provides-Extra: dev
Requires-Dist: twine ; extra == 'dev'
Requires-Dist: setuptools ; extra == 'dev'
